rvt/__init__.py
rvt/blend.py
rvt/blend_func.py
rvt/default.py
rvt/tile.py
rvt/vis.py
rvt_py-2.2.3.dist-info/LICENSE
rvt_py-2.2.3.dist-info/METADATA
rvt_py-2.2.3.dist-info/WHEEL
rvt_py-2.2.3.dist-info/top_level.txt
rvt_py-2.2.3.dist-info/RECORD
