Metadata-Version: 2.2
Name: rvt_py
Version: 2.2.3
Summary: Relief Visualization Toolbox Python library. It helps scientist visualize raster elevation model datasets. 
Home-page: https://github.com/EarthObservation/RVT_py
Author: ZRC SAZU and University of Ljubljana (UL FGG)
Author-email: ziga.kokalj@zrc-sazu.si
Project-URL: Documentation, https://rvt-py.readthedocs.io/en/latest/
Project-URL: Source, https://github.com/EarthObservation/RVT_py
Project-URL: Old RVT, https://iaps.zrc-sazu.si/en/rvt#v
Project-URL: ArcGIS Pro, https://github.com/EarthObservation/rvt-arcgis-pro
Project-URL: QGIS plugin, https://github.com/EarthObservation/rvt-qgis
Keywords: relief_visualization_toolbox relief_visualization relief rvt raster raster_visualization visualization
Classifier: Development Status :: 5 - Production/Stable
Classifier: Programming Language :: Python :: 3
Classifier: License :: OSI Approved :: Apache Software License
Classifier: Operating System :: OS Independent
Requires-Python: >=3.6, <3.12
License-File: LICENSE
Requires-Dist: numpy
Requires-Dist: scipy
Requires-Dist: gdal
Requires-Dist: matplotlib
Requires-Dist: pandas
Requires-Dist: geopandas
Requires-Dist: jupyter
Requires-Dist: rasterio
Dynamic: author
Dynamic: author-email
Dynamic: classifier
Dynamic: description
Dynamic: description-content-type
Dynamic: home-page
Dynamic: keywords
Dynamic: project-url
Dynamic: requires-dist
Dynamic: requires-python
Dynamic: summary
